odoo8_addon_website_backend_views-8.0.1.0.0.99.dev21-py3.8-nspkg.pth
odoo_addons/website_backend_views/README.rst
odoo_addons/website_backend_views/__init__.py
odoo_addons/website_backend_views/__openerp__.py
odoo_addons/website_backend_views/controllers/__init__.py
odoo_addons/website_backend_views/controllers/demo.py
odoo_addons/website_backend_views/i18n/af.po
odoo_addons/website_backend_views/i18n/am.po
odoo_addons/website_backend_views/i18n/ar.po
odoo_addons/website_backend_views/i18n/bg.po
odoo_addons/website_backend_views/i18n/bs.po
odoo_addons/website_backend_views/i18n/ca.po
odoo_addons/website_backend_views/i18n/cs.po
odoo_addons/website_backend_views/i18n/da.po
odoo_addons/website_backend_views/i18n/de.po
odoo_addons/website_backend_views/i18n/el.po
odoo_addons/website_backend_views/i18n/el_GR.po
odoo_addons/website_backend_views/i18n/en_GB.po
odoo_addons/website_backend_views/i18n/es.po
odoo_addons/website_backend_views/i18n/es_AR.po
odoo_addons/website_backend_views/i18n/es_CL.po
odoo_addons/website_backend_views/i18n/es_CO.po
odoo_addons/website_backend_views/i18n/es_CR.po
odoo_addons/website_backend_views/i18n/es_DO.po
odoo_addons/website_backend_views/i18n/es_EC.po
odoo_addons/website_backend_views/i18n/es_ES.po
odoo_addons/website_backend_views/i18n/es_MX.po
odoo_addons/website_backend_views/i18n/es_PE.po
odoo_addons/website_backend_views/i18n/es_PY.po
odoo_addons/website_backend_views/i18n/es_VE.po
odoo_addons/website_backend_views/i18n/et.po
odoo_addons/website_backend_views/i18n/eu.po
odoo_addons/website_backend_views/i18n/fa.po
odoo_addons/website_backend_views/i18n/fi.po
odoo_addons/website_backend_views/i18n/fr.po
odoo_addons/website_backend_views/i18n/fr_CA.po
odoo_addons/website_backend_views/i18n/fr_CH.po
odoo_addons/website_backend_views/i18n/gl.po
odoo_addons/website_backend_views/i18n/he.po
odoo_addons/website_backend_views/i18n/hr.po
odoo_addons/website_backend_views/i18n/hr_HR.po
odoo_addons/website_backend_views/i18n/hu.po
odoo8_addon_website_backend_views-8.0.1.0.0.99.dev21.dist-info/METADATA
odoo8_addon_website_backend_views-8.0.1.0.0.99.dev21.dist-info/WHEEL
odoo8_addon_website_backend_views-8.0.1.0.0.99.dev21.dist-info/namespace_packages.txt
odoo8_addon_website_backend_views-8.0.1.0.0.99.dev21.dist-info/top_level.txt
odoo8_addon_website_backend_views-8.0.1.0.0.99.dev21.dist-info/RECORD
